tests/__init__.py
tests/conftest.py
tests/test_unit_cf.py
tests/test_unit_structs.py
tongpo/__init__.py
tongpo/res/__init__.py
tongpo/res/cf/__init__.py
tongpo/res/cf/bit.py
tongpo/res/cf/boyorgirl.py
tongpo/res/cf/playoff.py
tongpo/res/cf/toolongstrings.py
tongpo/structs/__init__.py
tongpo-0.0.1.dist-info/LICENSE
tongpo-0.0.1.dist-info/METADATA
tongpo-0.0.1.dist-info/WHEEL
tongpo-0.0.1.dist-info/top_level.txt
tongpo-0.0.1.dist-info/RECORD
